nyt/nyt_comment_analysis.py
nyt_comments_analysis-0.1.dist-info/DESCRIPTION.rst
nyt_comments_analysis-0.1.dist-info/METADATA
nyt_comments_analysis-0.1.dist-info/RECORD
nyt_comments_analysis-0.1.dist-info/WHEEL
nyt_comments_analysis-0.1.dist-info/metadata.json
nyt_comments_analysis-0.1.dist-info/top_level.txt
