Metadata-Version: 2.0
Name: nyt-comments-analysis
Version: 0.1
Summary: A project written in Python to perform a sentiment analysis of the user comments made on nytimes.com using the Stanford CoreNLP.
Home-page: https://github.com/julianla/nyt-user-sentiment-analysis
Author: julianla
Author-email: UNKNOWN
License: MIT
Platform: UNKNOWN
